narupatools/__init__.py
narupatools/_version.py
narupatools/py.typed
narupatools/ase/__init__.py
narupatools/ase/converter.py
narupatools/ase/dynamics.py
narupatools/ase/imd_feature.py
narupatools/ase/null_calculator.py
narupatools/ase/runner.py
narupatools/ase/system.py
narupatools/ase/trajectory.py
narupatools/ase/constraints/__init__.py
narupatools/ase/constraints/constraint.py
narupatools/ase/constraints/imd_constraint.py
narupatools/ase/constraints/observer.py
narupatools/ase/openmm/__init__.py
narupatools/ase/openmm/calculator.py
narupatools/ase/openmm/converter.py
narupatools/ase/openmm/runner.py
narupatools/client/__init__.py
narupatools/client/client.py
narupatools/core/__init__.py
narupatools/core/dynamics.py
narupatools/core/event.py
narupatools/core/imd.py
narupatools/core/playable.py
narupatools/core/servable.py
narupatools/core/session.py
narupatools/core/trajectory.py
narupatools/frame/__init__.py
narupatools/frame/converter.py
narupatools/frame/frame_producer.py
narupatools/frame/frame_source.py
narupatools/lammps/__init__.py
narupatools/lammps/calculator.py
narupatools/lammps/converter.py
narupatools/mdanalysis/__init__.py
narupatools/mdanalysis/converter.py
narupatools/mdtraj/__init__.py
narupatools/mdtraj/converter.py
narupatools/mdtraj/trajectory.py
narupatools/nglview/__init__.py
narupatools/nglview/show.py
narupatools/nglview/structure.py
narupatools/openmm/__init__.py
narupatools/openmm/converter.py
narupatools/openmm/dynamics.py
narupatools/physics/__init__.py
narupatools/physics/force.py
narupatools/physics/matrix.py
narupatools/physics/rigidbody.py
narupatools/physics/typing.py
narupatools/physics/vector.py
narupatools/scivana/__init__.py
narupatools/scivana/multiplayer_avatar.py
narupatools/scivana/particle_selection.py
narupatools/scivana/shared_state.py
narupatools/scivana/visualisation.py
narupatools/state/__init__.py
narupatools/state/serializable_object.py
narupatools/state/state_object.py
narupatools/state/typing.py
narupatools-0.1.0.dist-info/LICENSE
narupatools-0.1.0.dist-info/METADATA
narupatools-0.1.0.dist-info/WHEEL
narupatools-0.1.0.dist-info/top_level.txt
narupatools-0.1.0.dist-info/RECORD
