Metadata-Version: 2.1
Name: narupatools
Version: 0.1.0
Summary: Tools and extensions for Narupa
Home-page: https://gitlab.com/alexjbinnie/narupatools
Author: 'Alex Jamieson-Binnie'
Author-email: alexjbinnie@alexjbinnie.com
License: UNKNOWN
Project-URL: Bug Tracker, https://gitlab.com/alexjbinnie/narupatools/-/issues
Project-URL: Changelog, https://gitlab.com/alexjbinnie/narupatools/-/blob/master/scivana/CHANGELOG
Platform: UNKNOWN
Classifier: Programming Language :: Python :: 3.7
Classifier: Programming Language :: Python :: 3.8
Classifier: Development Status :: 4 - Beta
Classifier: License :: OSI Approved :: GNU General Public License v3 (GPLv3)
Classifier: Operating System :: OS Independent
Requires-Python: >=3.7
Requires-Dist: ase (>=3.21)
Requires-Dist: openmm (>=7.2.0)
Requires-Dist: numpy (>=1.20.0)
